Metadata-Version: 2.1
Name: wordpress-auth
Version: 0.1.0
Summary: A Python package that provides WordPress authentication for Streamlit applications.
Home-page: https://github.com/Keyvanhardani/streamlit-wordpress-authentication
Author: Keyvan Hardani
Author-email: hello@keyvan.ai
License: UNKNOWN
Platform: UNKNOWN
Classifier: Development Status :: 3 - Alpha
Requires-Python: >=3.8
